setup.py
weasl/__init__.py
weasl.egg-info/PKG-INFO
weasl.egg-info/SOURCES.txt
weasl.egg-info/dependency_links.txt
weasl.egg-info/not-zip-safe
weasl.egg-info/top_level.txt