Metadata-Version: 1.0
Name: weasl
Version: 0.1
Summary: weakly supervised active learning framework
Home-page: https://github.com/njpataki/weasl
Author: Nicholas Pataki
Author-email: njpatakI@gmail.com
License: MIT
Platform: UNKNOWN
